Metadata-Version: 2.4
Name: pyflipper_gkfork
Version: 0.19
Summary: Unoffical Flipper Zero cli wrapper - forked from PyFlipper
Home-page: https://github.com/gabekassel/pyFlipper
Author: gabekassel
Author-email: gabe@gabekassel.com
License: MIT
Project-URL: Documentation, https://github.com/gabekassel/pyFlipper/blob/master/README.md
Project-URL: Bug Reports, https://github.com/gabekassel/pyFlipper/issues
Project-URL: Source Code, https://github.com/gabekassel/pyFlipper
Keywords: flipper,wrapper,module
Classifier: Development Status :: 4 - Beta
Classifier: Intended Audience :: Developers
Classifier: Topic :: Software Development :: Build Tools
Classifier: Programming Language :: Python :: 3.8
Classifier: Programming Language :: Python :: 3.9
Classifier: Programming Language :: Python :: 3.10
Classifier: License :: OSI Approved :: MIT License
Classifier: Operating System :: OS Independent
Requires-Python: >=3.8
License-File: LICENSE
Requires-Dist: pyserial
Requires-Dist: websocket-client
Dynamic: author
Dynamic: author-email
Dynamic: classifier
Dynamic: description
Dynamic: description-content-type
Dynamic: home-page
Dynamic: keywords
Dynamic: license
Dynamic: license-file
Dynamic: project-url
Dynamic: requires-dist
Dynamic: requires-python
Dynamic: summary
